tests/__init__.py
tests/test_utils.py
tests/test_datasources/__init__.py
tests/test_datasources/test_datasources.py
tests/test_datasources/test_ooi/__init__.py
tests/test_datasources/test_ooi/test_helpers.py
tests/test_datasources/test_ooi/test_ooi.py
yodapy/__init__.py
yodapy/_version.py
yodapy/datasources/__init__.py
yodapy/datasources/datasource.py
yodapy/datasources/ooi/CAVA.py
yodapy/datasources/ooi/OOI.py
yodapy/datasources/ooi/__init__.py
yodapy/datasources/ooi/helpers.py
yodapy/datasources/ooi/m2m.py
yodapy/datasources/ooi/m2m_client.py
yodapy/datasources/ooi/old_ooi.py
yodapy/datasources/ooi/ooi_m2m.py
yodapy/datasources/ooi/infrastructure/cava_arrays.csv
yodapy/datasources/ooi/infrastructure/cava_infrastructures.csv
yodapy/datasources/ooi/infrastructure/cava_instruments.csv
yodapy/datasources/ooi/infrastructure/cava_parameters.csv
yodapy/datasources/ooi/infrastructure/cava_sites.csv
yodapy/datasources/ooi/infrastructure/data_streams.csv
yodapy/datasources/ooi/infrastructure/instrument_classes.csv
yodapy/datasources/ooi/infrastructure/instrument_models.csv
yodapy/datasources/ooi/infrastructure/instruments.csv
yodapy/datasources/ooi/infrastructure/nodes.csv
yodapy/datasources/ooi/infrastructure/regions.csv
yodapy/datasources/ooi/infrastructure/sites.csv
yodapy/datasources/ooi/infrastructure/stream_descriptions.csv
yodapy/utils/__init__.py
yodapy/utils/conn.py
yodapy/utils/creds.py
yodapy/utils/files.py
yodapy/utils/meta.py
yodapy/utils/parser.py
yodapy-0.3.0b0.dist-info/LICENSE
yodapy-0.3.0b0.dist-info/METADATA
yodapy-0.3.0b0.dist-info/WHEEL
yodapy-0.3.0b0.dist-info/top_level.txt
yodapy-0.3.0b0.dist-info/RECORD
