Metadata-Version: 2.1
Name: yodapy
Version: 0.3.0b0
Summary: Your Ocean Data Access in Python
Home-page: UNKNOWN
Author: Landung Setiawan
Author-email: landungs@uw.edu
Maintainer: Landung Setiawan
Maintainer-email: landungs@uw.edu
License: MIT
Keywords: Ocean,Data,Access,OOI
Platform: UNKNOWN
Classifier: Development Status :: 3 - Alpha
Classifier: Intended Audience :: Developers
Classifier: Topic :: Software Development :: Build Tools
Classifier: License :: OSI Approved :: MIT License
Classifier: Operating System :: OS Independent
Classifier: Programming Language :: Python :: 3
Classifier: Programming Language :: Python :: 3.6
Classifier: Programming Language :: Python :: 3.7
Classifier: Topic :: Software Development :: Libraries :: Python Modules
Classifier: Topic :: Scientific/Engineering
Requires-Python: >=3
Requires-Dist: requests
Requires-Dist: pandas
Requires-Dist: xarray
Requires-Dist: matplotlib
Requires-Dist: lxml
Requires-Dist: grequests
Requires-Dist: gevent
Requires-Dist: gspread
Requires-Dist: siphon
Requires-Dist: dask
Requires-Dist: seaborn
Requires-Dist: netcdf4
Requires-Dist: oauth2client
Requires-Dist: progressbar2
Requires-Dist: s3fs
Requires-Dist: echopype
